xarray_treeview-2025.4.9.2.dist-info/METADATA
xarray_treeview-2025.4.9.2.dist-info/WHEEL
xarray_treeview-2025.4.9.2.dist-info/entry_points.txt
xarray_treeview-2025.4.9.2.dist-info/licenses/LICENSE
xarray_treeview/XarrayTreeModel.py
xarray_treeview/XarrayTreeView.py
xarray_treeview/XarrayTreeViewer.py
xarray_treeview/__init__.py
xarray_treeview/old/XarrayTreeItem.py
xarray_treeview/old/XarrayTreeModel.py
xarray_treeview/old/XarrayTreeView.py
xarray_treeview/old/XarrayTreeViewer.py
xarray_treeview-2025.4.9.2.dist-info/RECORD
