Metadata-Version: 2.1
Name: xarray-treeview
Version: 2025.4.9.2
Summary: PyQt/PySide model/view for tree of Xarray datasets.
Keywords: PyQt,PySide,xarray,tree
Author-Email: Marcel Goldschen-Ohm <goldschen-ohm@utexas.edu>
Classifier: Development Status :: 4 - Beta
Classifier: Intended Audience :: Developers
Classifier: License :: OSI Approved :: MIT License
Classifier: Programming Language :: Python :: 3 :: Only
Project-URL: homepage, https://github.com/marcel-goldschen-ohm/xarray-treeview
Project-URL: repository, https://github.com/marcel-goldschen-ohm/xarray-treeview
Project-URL: issues, https://github.com/marcel-goldschen-ohm/xarray-treeview/issues
Requires-Python: >=3.10
Requires-Dist: numpy>=1.26.2
Requires-Dist: xarray>=2025.3.1
Requires-Dist: qtpy>=2.4.1
Requires-Dist: qtawesome>=1.4.0
Requires-Dist: pyqt-ext>=2025.4.9.2
